digilog/__init__.py
digilog/_state.py
digilog/api.py
digilog/cli.py
digilog/client.py
digilog/config.py
digilog/exceptions.py
digilog/image_utils.py
digilog/py.typed
digilog/run.py
tests/__init__.py
tests/test_client.py
digilog-0.0.12.dist-info/METADATA
digilog-0.0.12.dist-info/WHEEL
digilog-0.0.12.dist-info/entry_points.txt
digilog-0.0.12.dist-info/top_level.txt
digilog-0.0.12.dist-info/RECORD
