Metadata-Version: 2.4
Name: digilog
Version: 0.0.12
Summary: Add your description here
Home-page: https://github.com/digilog/digilog-python
Author: Digilog Team
Author-email: team@digilog.com
Requires-Python: >=3.7
Requires-Dist: fastmcp>=0.1.0
Requires-Dist: matplotlib>=3.5.0
Requires-Dist: numpy>=1.21.0
Requires-Dist: requests>=2.25.0
Requires-Dist: typing-extensions>=3.7.4
Dynamic: author
Dynamic: author-email
Dynamic: home-page
Dynamic: requires-python
